llm_page_load/__init__.py
llm_page_load/algorithms/__init__.py
llm_page_load/algorithms/find_page_load_intelligent.py
llm_page_load/toolchain_llm/__init__.py
llm_page_load/toolchain_llm/adb_recorder_client.py
llm_page_load/toolchain_llm/server.py
llm_page_load/toolchain_llm/utils.py
llm_page_load/toolchain_llm/api/__init__.py
llm_page_load/toolchain_llm/api/app_traversal.py
llm_page_load/toolchain_llm/api/auitest.py
llm_page_load/toolchain_llm/api/by_pass.py
llm_page_load/toolchain_llm/api/campaign_analysis_server.py
llm_page_load/toolchain_llm/api/case_generation.py
llm_page_load/toolchain_llm/api/coe_service.py
llm_page_load/toolchain_llm/api/conversation.py
llm_page_load/toolchain_llm/api/es_service.py
llm_page_load/toolchain_llm/api/feature_api.py
llm_page_load/toolchain_llm/api/gpt_stream.py
llm_page_load/toolchain_llm/api/impact_analysis.py
llm_page_load/toolchain_llm/api/me_translation.py
llm_page_load/toolchain_llm/api/scenetivity_server.py
llm_page_load/toolchain_llm/api/trace_compare.py
llm_page_load/toolchain_llm/api/ui_detection.py
llm_page_load/toolchain_llm/api/urlscheme_query_classification.py
llm_page_load/toolchain_llm/api/components/__init__.py
llm_page_load/toolchain_llm/api/components/limiter.py
llm_page_load/toolchain_llm/config/__init__.py
llm_page_load/toolchain_llm/config/gunicorn.conf.py
llm_page_load/toolchain_llm/crane/__init__.py
llm_page_load/toolchain_llm/crane/cause_analysis.py
llm_page_load/toolchain_llm/crane/coe_sync_task.py
llm_page_load/toolchain_llm/crane/fund_judgement.py
llm_page_load/toolchain_llm/crane/mole_tag_analysis.py
llm_page_load/toolchain_llm/crane/tonotto_analysis_task.py
llm_page_load/toolchain_llm/deploy/__init__.py
llm_page_load/toolchain_llm/log/__init__.py
llm_page_load/toolchain_llm/scenetivity/__init__.py
llm_page_load/toolchain_llm/scenetivity/replacer.py
llm_page_load/toolchain_llm/service/GPT.py
llm_page_load/toolchain_llm/service/__init__.py
llm_page_load/toolchain_llm/service/claude3.py
llm_page_load-0.2.2.dist-info/METADATA
llm_page_load-0.2.2.dist-info/WHEEL
llm_page_load-0.2.2.dist-info/top_level.txt
llm_page_load-0.2.2.dist-info/RECORD
